brainyquote/__init__.py
brainyquote/pybrainyquote.py
brainyquote/test.py
brainyquote-0.2.dist-info/LICENSE.txt
brainyquote-0.2.dist-info/METADATA
brainyquote-0.2.dist-info/WHEEL
brainyquote-0.2.dist-info/top_level.txt
brainyquote-0.2.dist-info/RECORD
